MANIFEST.in
README.md
requirements.txt
setup.cfg
setup.py
contrib/Dockerfile
contrib/build-rpm.sh
contrib/des.service
contrib/rpmbuild.Dockerfile
des/__init__.py
des/arg.py
des/cli.py
des/log.py
des/runner.py
des/util.py
des/watcher.py
docker_event_scripts.egg-info/PKG-INFO
docker_event_scripts.egg-info/SOURCES.txt
docker_event_scripts.egg-info/dependency_links.txt
docker_event_scripts.egg-info/entry_points.txt
docker_event_scripts.egg-info/requires.txt
docker_event_scripts.egg-info/top_level.txt