Metadata-Version: 1.1
Name: docker-event-scripts
Version: 0.1.0
Summary: Run scripts in response to Docker events.
Home-page: https://github.com/colebrumley/des
Author: Cole Brumley
Author-email: cole.brumley@gmail.com
License: BSD
Download-URL: https://github.com/colebrumley/des/tarball/0.1.0
Keywords: docker event watch monitor script
Platform: UNKNOWN
Classifier: Development Status :: 3 - Alpha
Classifier: Intended Audience :: Developers
Classifier: Programming Language :: Python :: 3
